html2json/__init__.py
html2json/parser.py
bs4_html2json-0.0.3.dist-info/LICENSE
bs4_html2json-0.0.3.dist-info/METADATA
bs4_html2json-0.0.3.dist-info/WHEEL
bs4_html2json-0.0.3.dist-info/top_level.txt
bs4_html2json-0.0.3.dist-info/RECORD
