Metadata-Version: 2.1
Name: bs4_html2json
Version: 0.0.3
Summary: A simple wrapper for adding a simple way for storing parsed HTML content
Author-email: Jason Jiménez Cruz <jasonjimenezcruz@gmail.com>
License: MIT License
Project-URL: Homepage, https://github.com/jasonjimnz/beautiful_soup4_html2json
Project-URL: Issues, https://github.com/jasonjimnz/beautiful_soup4_html2json/issues
Classifier: Development Status :: 3 - Alpha
Classifier: Programming Language :: Python :: 3.9
Classifier: License :: OSI Approved :: MIT License
Classifier: Operating System :: OS Independent
Classifier: Intended Audience :: Developers
Requires-Python: >=3.9
License-File: LICENSE
Requires-Dist: beautifulsoup4
Requires-Dist: requests
